{
    "setting": {},
    "condition": {
        "plugin": {
            "list": []
        },
        "game": {
            "list": []
        },
        "gamePlugin": {
            "list": []
        },
        "miniprogram": {
            "list": [
                {
                    "id": -1,
                    "name": "me",
                    "pathName": "pages/me/me",
                    "query": "",
                    "scene": null
                },
                {
                    "id": -1,
                    "name": "booklist",
                    "pathName": "pages/booklist/booklist",
                    "query": "",
                    "scene": null
                },
                {
                    "name": "bookdetail",
                    "pathName": "pages/bookdetail/bookdetail",
                    "query": "id=54ad1eea61f0c4160aebfa640ca9d4a8",
                    "launchMode": "default",
                    "scene": null
                },
                {
                    "name": "",
                    "pathName": "page/feedback/feedback",
                    "query": "",
                    "launchMode": "default",
                    "scene": null
                },
                {
                    "name": "",
                    "pathName": "pages/login/login",
                    "query": "",
                    "scene": null,
                    "launchMode": "default"
                }
            ]
        }
    }
}